bdaeslab/__init__.py
bdaeslab/main.py
bdaeslab/codes/1.txt
bdaeslab/codes/10.txt
bdaeslab/codes/2.txt
bdaeslab/codes/3.txt
bdaeslab/codes/4.txt
bdaeslab/codes/5.txt
bdaeslab/codes/6.txt
bdaeslab/codes/7.txt
bdaeslab/codes/9.txt
bdaeslab-0.0.1.dist-info/METADATA
bdaeslab-0.0.1.dist-info/WHEEL
bdaeslab-0.0.1.dist-info/top_level.txt
bdaeslab-0.0.1.dist-info/RECORD
