Metadata-Version: 2.4
Name: bdaeslab
Version: 0.0.1
Summary: A Python package that retrieves code snippets by number
Author: bdaeslab
License: MIT
